tileputty/__init__.py
tileputty/upload_tiles.py
tileputty-0.2.5.dist-info/LICENSE
tileputty-0.2.5.dist-info/METADATA
tileputty-0.2.5.dist-info/WHEEL
tileputty-0.2.5.dist-info/entry_points.txt
tileputty-0.2.5.dist-info/top_level.txt
tileputty-0.2.5.dist-info/RECORD
